odoo/addons/account_bank_statement_import_mt940_base/README.rst
odoo/addons/account_bank_statement_import_mt940_base/__init__.py
odoo/addons/account_bank_statement_import_mt940_base/__manifest__.py
odoo/addons/account_bank_statement_import_mt940_base/mt940.py
odoo/addons/account_bank_statement_import_mt940_base/test_files/test-ing.940
odoo/addons/account_bank_statement_import_mt940_base/test_files/test-rabo.swi
odoo/addons/account_bank_statement_import_mt940_base/test_files/test-sns.940
odoo/addons/account_bank_statement_import_mt940_base/test_files/test-wrong-file.940
odoo/addons/account_bank_statement_import_mt940_base/tests/__init__.py
odoo/addons/account_bank_statement_import_mt940_base/tests/test_import_bank_statement.py
odoo11_addon_account_bank_statement_import_mt940_base-11.0.1.0.0.dist-info/DESCRIPTION.rst
odoo11_addon_account_bank_statement_import_mt940_base-11.0.1.0.0.dist-info/METADATA
odoo11_addon_account_bank_statement_import_mt940_base-11.0.1.0.0.dist-info/RECORD
odoo11_addon_account_bank_statement_import_mt940_base-11.0.1.0.0.dist-info/WHEEL
odoo11_addon_account_bank_statement_import_mt940_base-11.0.1.0.0.dist-info/metadata.json
odoo11_addon_account_bank_statement_import_mt940_base-11.0.1.0.0.dist-info/top_level.txt
